chainai/__init__.py
chainai/_interfaces.py
chainai/id_generator.py
chainai/_schema/__init__.py
chainai/_schema/schema.py
chainai/_utils/__init__.py
chainai/_utils/graph.py
chainai/blocks/__init__.py
chainai/blocks/definition.py
chainai/config/__init__.py
chainai/config/_parser.py
chainai/connector/__init__.py
chainai/connector/_connector.py
chainai/runner/__init__.py
chainai-0.0.2.dist-info/LICENSE
chainai-0.0.2.dist-info/METADATA
chainai-0.0.2.dist-info/WHEEL
chainai-0.0.2.dist-info/top_level.txt
chainai-0.0.2.dist-info/RECORD
