Metadata-Version: 2.1
Name: chainai
Version: 0.0.2
Summary: Python SDK for ChainAI's integrated AI agent platform.
License: BSD-3-Clause
License-File: LICENSE
